pydantic_ai_skills/__init__.py
pydantic_ai_skills/directory.py
pydantic_ai_skills/exceptions.py
pydantic_ai_skills/local.py
pydantic_ai_skills/toolset.py
pydantic_ai_skills/types.py
pydantic_ai_skills-0.4.0.dist-info/METADATA
pydantic_ai_skills-0.4.0.dist-info/WHEEL
pydantic_ai_skills-0.4.0.dist-info/licenses/LICENSE
pydantic_ai_skills-0.4.0.dist-info/RECORD
