Metadata-Version: 2.4
Name: pydantic-ai-skills
Version: 0.4.0
Summary: A lightweight agent skill implementation for Pydantic AI
Project-URL: Homepage, https://github.com/dougtrajano/pydantic-ai-skills
Project-URL: Source, https://github.com/dougtrajano/pydantic-ai-skills
Author-email: Douglas Trajano <douglas.trajano@outlook.com>
License-Expression: MIT
License-File: LICENSE
Classifier: Development Status :: 3 - Alpha
Classifier: Intended Audience :: Developers
Classifier: Intended Audience :: Information Technology
Classifier: Operating System :: OS Independent
Classifier: Programming Language :: Python
Classifier: Programming Language :: Python :: 3
Classifier: Programming Language :: Python :: 3 :: Only
Classifier: Programming Language :: Python :: 3.10
Classifier: Programming Language :: Python :: 3.11
Classifier: Programming Language :: Python :: 3.12
Classifier: Programming Language :: Python :: 3.13
Classifier: Topic :: Software Development :: Libraries :: Python Modules
Requires-Python: >=3.10
Requires-Dist: anyio>=4.0.0
Requires-Dist: pydantic-ai-slim>=0.5.0
Requires-Dist: pyyaml>=6.0
Provides-Extra: docs
Requires-Dist: mkdocs-git-revision-date-localized-plugin>=1.5.0; extra == 'docs'
Requires-Dist: mkdocs-material-extensions>=1.3.1; extra == 'docs'
Requires-Dist: mkdocs-material>=9.7.1; extra == 'docs'
Requires-Dist: mkdocs-section-index>=0.3.10; extra == 'docs'
Requires-Dist: mkdocs-tooltips>=0.1.0; extra == 'docs'
Requires-Dist: mkdocs>=1.6.1; extra == 'docs'
Requires-Dist: mkdocstrings[python]>=1.0.0; extra == 'docs'
Provides-Extra: test
Requires-Dist: pytest-asyncio>=0.23.0; extra == 'test'
Requires-Dist: pytest-cov>=4.1.0; extra == 'test'
Requires-Dist: pytest>=8.0.0; extra == 'test'
Requires-Dist: types-pyyaml>=6.0.12; extra == 'test'
